{"list":[{"date":"2018-01","arr":{"year":2018,"month":1,"link":["2018-01-27_水鸟知寒.JPG","2018-01-27_雪人.JPG","2018-01-27_雪覆地，冰冻湖岸.JPG"],"text":["水鸟知寒","雪人","雪覆地，冰冻湖岸"],"type":["image","image","image"]}},{"date":"2017-11","arr":{"year":2017,"month":11,"link":["2017-11-04_汤逊湖.jpg","2017-11-04_汤逊湖0947.jpg","2017-11-04_汤逊湖1058.jpg","2017-11-04_汤逊湖1123.jpg","2017-11-08_武汉工程大学.jpg","2017-11-16_汉阳造1500.jpg"],"text":["汤逊湖","汤逊湖0947","汤逊湖1058","汤逊湖1123","武汉工程大学","汉阳造1500"],"type":["image","image","image","image","image","image"]}},{"date":"2017-09","arr":{"year":2017,"month":9,"link":["2017-09-17_ICIP2017.JPG","2017-09-18_北京奥林匹克公园.JPG","2017-09-18_未名湖1332.JPG","2017-09-19_胡同.JPG","2017-09-19_胡同1212.JPG","2017-09-19_胡同1302.JPG","2017-09-20_798.JPG","2017-09-20_798木木美术馆1811.JPG","2017-09-20_798木木美术馆1812.JPG","2017-09-21_故宫筒子河.JPG"],"text":["ICIP2017","北京奥林匹克公园","未名湖1332","胡同","胡同1212","胡同1302","798","798木木美术馆1811","798木木美术馆1812","故宫筒子河"],"type":["image","image","image","image","image","image","image","image","image","image"]}},{"date":"2017-01","arr":{"year":2017,"month":1,"link":["2017-01-16_汉阳造1435.JPG","2017-01-16_汉阳造1443.JPG","2017-01-16_汉阳造1458.JPG","2017-01-16_汉阳造1503.JPG","2017-01-28_HACK0431.jpg"],"text":["汉阳造1435","汉阳造1443","汉阳造1458","汉阳造1503","HACK0431"],"type":["image","image","image","image","image"]}},{"date":"2016-11","arr":{"year":2016,"month":11,"link":["2016-11-20_dating.JPG"],"text":["dating"],"type":["image"]}},{"date":"2016-06","arr":{"year":2016,"month":6,"link":["2016-06-25_烟台1.JPG","2016-06-30_烟台2.JPG","2016-06-30_烟台3.JPG","2016-06-30_烟台4.JPG","2016-06-30_烟台5.JPG","2016-06-30_烟台6.JPG","2016-06-30_烟台7.JPG"],"text":["烟台1","烟台2","烟台3","烟台4","烟台5","烟台6","烟台7"],"type":["image","image","image","image","image","image","image"]}}]}